antispam/__init__.py
antispam/akismet/__init__.py
antispam/akismet/client.py
antispam/akismet/entities.py
antispam/akismet/utils.py
antispam/captcha/__init__.py
antispam/captcha/default_settings.py
antispam/captcha/forms.py
antispam/captcha/widgets.py
antispam/captcha/templatetags/__init__.py
antispam/captcha/templatetags/recaptcha.py
antispam/honeypot/__init__.py
antispam/honeypot/forms.py
antispam/honeypot/widgets.py
django_antispam-1.0.3.dist-info/LICENSE
django_antispam-1.0.3.dist-info/METADATA
django_antispam-1.0.3.dist-info/WHEEL
django_antispam-1.0.3.dist-info/top_level.txt
django_antispam-1.0.3.dist-info/RECORD
