Metadata-Version: 2.1
Name: django-antispam
Version: 1.0.3
Summary: Anti-spam protection tools for django applications.
Home-page: https://github.com/mixkorshun/django-antispam
Author: Vladislav Bakin
Author-email: mixkorshun@gmail.com
Maintainer: Vladislav Bakin
Maintainer-email: mixkorshun@gmail.com
License: MIT
Keywords: anti-spam,antispam,spam
Platform: UNKNOWN
Classifier: Development Status :: 5 - Production/Stable
Classifier: Intended Audience :: Developers
Classifier: Environment :: Web Environment
Classifier: Framework :: Django
Classifier: Natural Language :: English
Classifier: License :: OSI Approved :: MIT License
Classifier: Programming Language :: Python
Classifier: Programming Language :: Python :: 3
Classifier: Programming Language :: Python :: 3.4
Classifier: Programming Language :: Python :: 3.5
Classifier: Programming Language :: Python :: 3.6
Classifier: Programming Language :: Python :: 3.7
Requires-Dist: django
Requires-Dist: python-akismet
